narrative_flow/__init__.py
narrative_flow/cli.py
narrative_flow/executor.py
narrative_flow/logger.py
narrative_flow/logging_config.py
narrative_flow/models.py
narrative_flow/parser.py
narrative_flow/py.typed
narrative_flow/utils.py
narrative_flow-1.1.0.dist-info/METADATA
narrative_flow-1.1.0.dist-info/WHEEL
narrative_flow-1.1.0.dist-info/entry_points.txt
narrative_flow-1.1.0.dist-info/licenses/LICENSE
narrative_flow-1.1.0.dist-info/RECORD
