Metadata-Version: 2.4
Name: narrative-flow
Version: 1.1.0
Summary: Human-readable LLM conversation workflows
Project-URL: Homepage, https://github.com/hpowers/narrative-flow
Project-URL: Documentation, https://github.com/hpowers/narrative-flow#readme
Project-URL: Repository, https://github.com/hpowers/narrative-flow
Project-URL: Issues, https://github.com/hpowers/narrative-flow/issues
Author-email: Hunter Powers <hunter@wiretheplanet.com>
License: MIT License
License-File: LICENSE
Keywords: ai,automation,chatgpt,claude,conversation,gemini,llm,openrouter,workflow
Classifier: Development Status :: 3 - Alpha
Classifier: Intended Audience :: Developers
Classifier: License :: OSI Approved :: MIT License
Classifier: Operating System :: OS Independent
Classifier: Programming Language :: Python :: 3
Classifier: Programming Language :: Python :: 3.10
Classifier: Programming Language :: Python :: 3.11
Classifier: Programming Language :: Python :: 3.12
Classifier: Programming Language :: Python :: 3.13
Classifier: Topic :: Scientific/Engineering :: Artificial Intelligence
Classifier: Topic :: Software Development :: Libraries :: Python Modules
Classifier: Typing :: Typed
Requires-Python: >=3.10
Requires-Dist: httpx>=0.27
Requires-Dist: jinja2>=3.1
Requires-Dist: pydantic>=2.0
Requires-Dist: python-frontmatter>=1.0.0
Requires-Dist: pyyaml>=6.0
Provides-Extra: dev
Requires-Dist: pre-commit>=4.0; extra == 'dev'
Requires-Dist: pytest-httpx>=0.30; extra == 'dev'
Requires-Dist: pytest>=8.0; extra == 'dev'
Requires-Dist: ruff>=0.14; extra == 'dev'
